magic/__init__.py
magic/calculator.py
magic/constants.py
magic/curve.py
magic/interface.py
magic/data/ligo/20160824T161306.mat
magic/data/ligo/ETM_layers_151221_2150.mat
magic/data/ligo/ITM_layers_151221_2237.mat
magic/data/ligo/VOYAGER_int_noise_no_rad_press.kat
magic/data/ligo/VOYAGER_int_noise_rad_press.kat
magic/data/ligo/VOYAGER_quantum.kat
magic/data/ligo/balanced_VOYAGER_int_noise_rad_pres.kat
magic/data/ligo/quad_optimized_masses_for_PUM_with_springs.mat
magic/detectors/__init__.py
magic/detectors/advanced_ligo.py
magic/detectors/cosmic_explorer.py
magic/detectors/einstein_telescope.py
magic/detectors/ifoParent.py
magic/detectors/voyager.py
magic/materials/__init__.py
magic/materials/materialParent.py
magic/materials/mirror/__init__.py
magic/materials/mirror/silica.py
magic/materials/mirror/silicon.py
magic/materials/suspension/__init__.py
magic/materials/suspension/c70steel.py
magic/materials/suspension/marsteel.py
magic/materials/suspension/silica.py
magic/materials/suspension/silicon.py
magic/noise/__init__.py
magic/noise/noiseParent.py
magic/noise/et/__init__.py
magic/noise/et/blackforestnewtonian.py
magic/noise/et/blackforestseismic.py
magic/noise/ligo/__init__.py
magic/noise/ligo/carrierdensity.py
magic/noise/ligo/coatingbrownian.py
magic/noise/ligo/coatingthermooptic.py
magic/noise/ligo/finessequantum.py
magic/noise/ligo/newtonian.py
magic/noise/ligo/quantum.py
magic/noise/ligo/residualgas.py
magic/noise/ligo/seismic.py
magic/noise/ligo/substratebrownian.py
magic/noise/ligo/substratethermoelastic.py
magic/noise/ligo/suspensionthermal.py
magic/noise/ligo/thermorefractive.py
magic/optimisation/costs.py
magic/optimisation/detector_range.py
magic/optimisation/differential_evolution_distance.py
magic/optimisation/downsample_signal.py
magic/optimisation/plot_noises.py
magic/optimisation/sourcesignals/2HHybrids1.dat
magic/optimisation/sourcesignals/HBHybrids1.dat
magic/optimisation/sourcesignals/eosavglist.dat
magic/tools/__init__.py
ifomagic-0.0.5.dist-info/LICENSE
ifomagic-0.0.5.dist-info/METADATA
ifomagic-0.0.5.dist-info/WHEEL
ifomagic-0.0.5.dist-info/top_level.txt
ifomagic-0.0.5.dist-info/RECORD
