Metadata-Version: 2.1
Name: ifomagic
Version: 0.0.5
Summary: UNKNOWN
Home-page: http://gitlab.sr.bham.ac.uk/ifolab/MAGIC/tree/master/Code
Author: Isobel Romero-Shaw, Roshni Vincent, Andreas Freise
Author-email: isobel.romeroshaw@gmail.com
License: UNKNOWN
Platform: UNKNOWN
Classifier: Programming Language :: Python :: 3
Classifier: License :: OSI Approved :: MIT License
Classifier: Operating System :: OS Independent
Requires-Dist: pykat
Requires-Dist: seaborn
